<?xml version="1.0" encoding="UTF-8" standalone="no"?>
<!DOCTYPE svg PUBLIC "-//W3C//DTD SVG 1.0//EN"
 "http://www.w3.org/TR/2001/REC-SVG-20010904/DTD/svg10.dtd" [
 <!ATTLIST svg xmlns:xlink CDATA #FIXED "http://www.w3.org/1999/xlink">
]>
<!-- Generated by Graphviz version 2.14.1 (Fri Sep  7 12:22:15 UTC 2007)
     For user: (myexperiment) myExperiment User -->
<!-- Title: t2flow_graph Pages: 1 -->
<svg width="176pt" height="227pt"
 viewBox="0.00 0.00 176.00 227.00" xmlns="http://www.w3.org/2000/svg" xmlns:xlink="http://www.w3.org/1999/xlink">
<g id="graph0" class="graph" transform="scale(1 1) rotate(0) translate(4 223)">
<title>t2flow_graph</title>
<polygon style="fill:white;stroke:white;" points="-4,4 -4,-223 172,-223 172,4 -4,4"/>
<g id="cluster2" class="cluster"><title>cluster_sinks</title>
<polygon style="fill:none;stroke:black;stroke-dasharray:1,5;" points="46,-16 46,-75 160,-75 160,-16 46,-16"/>
<text text-anchor="middle" x="94" y="-62" style="font-family:Arial;font-size:10.00;">Workflow Outputs</text>
</g>
<!-- url -->
<g id="node1" class="node"><title>url</title>
<polygon style="fill:lightsteelblue;stroke:black;" points="58,-218.5 30,-218.5 30,-197.5 58,-197.5 58,-218.5"/>
<text text-anchor="middle" x="44" y="-205" style="font-family:Arial;font-size:10.00;">url</text>
</g>
<!-- getFileFromUrl -->
<g id="node2" class="node"><title>getFileFromUrl</title>
<polygon style="fill:white;stroke:black;" points="88,-180.5 4.26326e-14,-180.5 0,-159.5 88,-159.5 88,-180.5"/>
<text text-anchor="middle" x="44" y="-167" style="font-family:Arial;font-size:10.00;">getFileFromUrl</text>
</g>
<!-- url&#45;&gt;getFileFromUrl -->
<g id="edge3" class="edge"><title>url&#45;&gt;getFileFromUrl</title>
<path style="fill:none;stroke:black;" d="M44,-197C44,-195 44,-193 44,-191"/>
<polygon style="fill:black;stroke:black;" points="47.5001,-191 44,-181 40.5001,-191 47.5001,-191"/>
</g>
<!-- Write_Text_File -->
<g id="node4" class="node"><title>Write_Text_File</title>
<polygon style="fill:white;stroke:black;" points="114,-142.5 22,-142.5 22,-121.5 114,-121.5 114,-142.5"/>
<text text-anchor="middle" x="68" y="-129" style="font-family:Arial;font-size:10.00;">Write_Text_File</text>
</g>
<!-- getFileFromUrl&#45;&gt;Write_Text_File -->
<g id="edge7" class="edge"><title>getFileFromUrl&#45;&gt;Write_Text_File</title>
<path style="fill:none;stroke:black;" d="M51,-159C52,-157 54,-154 56,-152"/>
<polygon style="fill:black;stroke:black;" points="59.2031,-153.441 61,-143 53.084,-150.042 59.2031,-153.441"/>
</g>
<!-- startCytoscape -->
<g id="node3" class="node"><title>startCytoscape</title>
<polygon style="fill:#eec591;stroke:black;" points="157,-104.5 75,-104.5 75,-83.5 157,-83.5 157,-104.5"/>
<text text-anchor="middle" x="116" y="-91" style="font-family:Arial;font-size:10.00;">startCytoscape</text>
</g>
<!-- WORKFLOWINTERNALSINK_status -->
<g id="node9" class="node"><title>WORKFLOWINTERNALSINK_status</title>
<polygon style="fill:#bcd2ee;stroke:black;" points="134,-45.5 92,-45.5 92,-24.5 134,-24.5 134,-45.5"/>
<text text-anchor="middle" x="113" y="-32" style="font-family:Arial;font-size:10.00;">status</text>
</g>
<!-- startCytoscape&#45;&gt;WORKFLOWINTERNALSINK_status -->
<g id="edge13" class="edge"><title>startCytoscape&#45;&gt;WORKFLOWINTERNALSINK_status</title>
<path style="fill:none;stroke:black;" d="M115,-83C115,-75 115,-65 114,-56"/>
<polygon style="fill:black;stroke:black;" points="117.5,-56 114,-46 110.5,-56 117.5,-56"/>
</g>
<!-- Write_Text_File&#45;&gt;startCytoscape -->
<g id="edge15" class="edge"><title>Write_Text_File&#45;&gt;startCytoscape</title>
<path style="fill:none;stroke:gray;" d="M81,-121C86,-118 91,-114 96,-110"/>
<ellipse style="fill:none;stroke:gray;" cx="98.9271" cy="-107.561" rx="4.00002" ry="4.00002"/>
</g>
<!-- WORKFLOWINTERNALSINK_data -->
<g id="node8" class="node"><title>WORKFLOWINTERNALSINK_data</title>
<polygon style="fill:#bcd2ee;stroke:black;" points="88,-45.5 54,-45.5 54,-24.5 88,-24.5 88,-45.5"/>
<text text-anchor="middle" x="71" y="-32" style="font-family:Arial;font-size:10.00;">data</text>
</g>
<!-- Write_Text_File&#45;&gt;WORKFLOWINTERNALSINK_data -->
<g id="edge11" class="edge"><title>Write_Text_File&#45;&gt;WORKFLOWINTERNALSINK_data</title>
<path style="fill:none;stroke:black;" d="M68,-121C69,-105 70,-76 71,-56"/>
<polygon style="fill:black;stroke:black;" points="74.5001,-56 71,-46 67.5001,-56 74.5001,-56"/>
</g>
<!-- tempFile -->
<g id="node5" class="node"><title>tempFile</title>
<polygon style="fill:lightsteelblue;stroke:black;" points="150,-180.5 92,-180.5 92,-159.5 150,-159.5 150,-180.5"/>
<text text-anchor="middle" x="121" y="-167" style="font-family:Arial;font-size:10.00;">tempFile</text>
</g>
<!-- tempFile&#45;&gt;startCytoscape -->
<g id="edge5" class="edge"><title>tempFile&#45;&gt;startCytoscape</title>
<path style="fill:none;stroke:black;" d="M120,-159C119,-148 118,-129 118,-115"/>
<polygon style="fill:black;stroke:black;" points="121.478,-114.602 117,-105 114.512,-115.299 121.478,-114.602"/>
</g>
<!-- tempFile&#45;&gt;Write_Text_File -->
<g id="edge9" class="edge"><title>tempFile&#45;&gt;Write_Text_File</title>
<path style="fill:none;stroke:black;" d="M106,-159C102,-156 96,-152 92,-149"/>
<polygon style="fill:black;stroke:black;" points="93.262,-145.635 83,-143 89.3791,-151.459 93.262,-145.635"/>
</g>
<!-- WORKFLOWINTERNALSINKCONTROL -->
<g id="node7" class="node"><title>WORKFLOWINTERNALSINKCONTROL</title>
<polygon style="fill:#66cd00;stroke:black;" points="145,-28 152,-38.5 138,-38.5 145,-28"/>
</g>
</g>
</svg>
