<?xml version="1.0" encoding="UTF-8" standalone="no"?>
<!DOCTYPE svg PUBLIC "-//W3C//DTD SVG 1.0//EN"
 "http://www.w3.org/TR/2001/REC-SVG-20010904/DTD/svg10.dtd" [
 <!ATTLIST svg xmlns:xlink CDATA #FIXED "http://www.w3.org/1999/xlink">
]>
<!-- Generated by Graphviz version 2.14.1 (Fri Sep  7 12:22:15 UTC 2007)
     For user: (myexperiment) myExperiment User -->
<!-- Title: scufl_graph Pages: 1 -->
<svg width="122pt" height="188pt"
 viewBox="0.00 0.00 122.00 188.00" xmlns="http://www.w3.org/2000/svg" xmlns:xlink="http://www.w3.org/1999/xlink">
<g id="graph0" class="graph" transform="scale(1 1) rotate(0) translate(4 184)">
<title>scufl_graph</title>
<polygon style="fill:white;stroke:white;" points="-4,4 -4,-184 118,-184 118,4 -4,4"/>
<g id="cluster2" class="cluster"><title>cluster_sources</title>
<polygon style="fill:none;stroke:black;stroke-dasharray:1,5;" points="9,-113 9,-172 105,-172 105,-113 9,-113"/>
<text text-anchor="middle" x="53" y="-159" style="font-family:Arial;font-size:10.00;">Workflow Inputs</text>
</g>
<g id="cluster3" class="cluster"><title>cluster_sinks</title>
<polygon style="fill:none;stroke:black;stroke-dasharray:1,5;" points="8,-16 8,-75 106,-75 106,-16 8,-16"/>
<text text-anchor="middle" x="56" y="-62" style="font-family:Arial;font-size:10.00;">Workflow Outputs</text>
</g>
<!-- getSynonyms -->
<g id="node1" class="node"><title>getSynonyms</title>
<polygon style="fill:#a2cd5a;stroke:black;" points="87,-104.5 9,-104.5 9,-83.5 87,-83.5 87,-104.5"/>
<text text-anchor="middle" x="48" y="-91" style="font-family:Arial;font-size:10.00;">getSynonyms</text>
</g>
<!-- WORKFLOWINTERNALSINK_Synonyms -->
<g id="node7" class="node"><title>WORKFLOWINTERNALSINK_Synonyms</title>
<polygon style="fill:#bcd2ee;stroke:black;" points="80,-45.5 16,-45.5 16,-24.5 80,-24.5 80,-45.5"/>
<text text-anchor="middle" x="48" y="-32" style="font-family:Arial;font-size:10.00;">Synonyms</text>
</g>
<!-- getSynonyms&#45;&gt;WORKFLOWINTERNALSINK_Synonyms -->
<g id="edge6" class="edge"><title>getSynonyms&#45;&gt;WORKFLOWINTERNALSINK_Synonyms</title>
<path style="fill:none;stroke:black;" d="M48,-83C48,-75 48,-65 48,-56"/>
<polygon style="fill:black;stroke:black;" points="51.5001,-56 48,-46 44.5001,-56 51.5001,-56"/>
</g>
<!-- WORKFLOWINTERNALSOURCECONTROL -->
<g id="node3" class="node"><title>WORKFLOWINTERNALSOURCECONTROL</title>
<polygon style="fill:#ff4040;stroke:black;" points="90,-139 83,-128.5 97,-128.5 90,-139"/>
</g>
<!-- WORKFLOWINTERNALSOURCE_SBML&#45;file -->
<g id="node4" class="node"><title>WORKFLOWINTERNALSOURCE_SBML&#45;file</title>
<polygon style="fill:skyblue;stroke:black;" points="79,-142.5 17,-142.5 17,-121.5 79,-121.5 79,-142.5"/>
<text text-anchor="middle" x="48" y="-129" style="font-family:Arial;font-size:10.00;">SBML&#45;file</text>
</g>
<!-- WORKFLOWINTERNALSOURCE_SBML&#45;file&#45;&gt;getSynonyms -->
<g id="edge4" class="edge"><title>WORKFLOWINTERNALSOURCE_SBML&#45;file&#45;&gt;getSynonyms</title>
<path style="fill:none;stroke:black;" d="M48,-121C48,-119 48,-117 48,-115"/>
<polygon style="fill:black;stroke:black;" points="51.5001,-115 48,-105 44.5001,-115 51.5001,-115"/>
</g>
<!-- WORKFLOWINTERNALSINKCONTROL -->
<g id="node6" class="node"><title>WORKFLOWINTERNALSINKCONTROL</title>
<polygon style="fill:#66cd00;stroke:black;" points="91,-28 98,-38.5 84,-38.5 91,-28"/>
</g>
</g>
</svg>
