<?xml version="1.0" encoding="UTF-8" standalone="no"?>
<!DOCTYPE svg PUBLIC "-//W3C//DTD SVG 1.0//EN"
 "http://www.w3.org/TR/2001/REC-SVG-20010904/DTD/svg10.dtd" [
 <!ATTLIST svg xmlns:xlink CDATA #FIXED "http://www.w3.org/1999/xlink">
]>
<!-- Generated by Graphviz version 2.14.1 (Fri Sep  7 12:22:15 UTC 2007)
     For user: (myexperiment) myExperiment User -->
<!-- Title: t2flow_graph Pages: 1 -->
<svg width="736pt" height="264pt"
 viewBox="0.00 0.00 736.00 264.00" xmlns="http://www.w3.org/2000/svg" xmlns:xlink="http://www.w3.org/1999/xlink">
<g id="graph0" class="graph" transform="scale(1 1) rotate(0) translate(4 260)">
<title>t2flow_graph</title>
<polygon style="fill:white;stroke:white;" points="-4,4 -4,-260 732,-260 732,4 -4,4"/>
<g id="cluster2" class="cluster"><title>cluster_sources</title>
<polygon style="fill:none;stroke:black;stroke-dasharray:1,5;" points="123,-189 123,-248 337,-248 337,-189 123,-189"/>
<text text-anchor="middle" x="167" y="-235" style="font-family:Arial;font-size:10.00;">Workflow Inputs</text>
</g>
<g id="cluster3" class="cluster"><title>cluster_sinks</title>
<polygon style="fill:none;stroke:black;stroke-dasharray:1,5;" points="132,-16 132,-75 516,-75 516,-16 132,-16"/>
<text text-anchor="middle" x="180" y="-62" style="font-family:Arial;font-size:10.00;">Workflow Outputs</text>
</g>
<!-- sentenceListNormaliser -->
<g id="node1" class="node"><title>sentenceListNormaliser</title>
<polygon style="fill:#eec591;stroke:black;" points="348,-180.5 220,-180.5 220,-159.5 348,-159.5 348,-180.5"/>
<text text-anchor="middle" x="284" y="-167" style="font-family:Arial;font-size:10.00;">sentenceListNormaliser</text>
</g>
<!-- analyze -->
<g id="node2" class="node"><title>analyze</title>
<polygon style="fill:white;stroke:black;" points="438,-142.5 386,-142.5 386,-121.5 438,-121.5 438,-142.5"/>
<text text-anchor="middle" x="412" y="-129" style="font-family:Arial;font-size:10.00;">analyze</text>
</g>
<!-- sentenceListNormaliser&#45;&gt;analyze -->
<g id="edge14" class="edge"><title>sentenceListNormaliser&#45;&gt;analyze</title>
<path style="fill:none;stroke:black;" d="M320,-159C338,-154 359,-148 376,-143"/>
<polygon style="fill:black;stroke:black;" points="377.427,-146.226 386,-140 375.416,-139.521 377.427,-146.226"/>
</g>
<!-- jamesXPath -->
<g id="node7" class="node"><title>jamesXPath</title>
<polygon style="fill:#eec591;stroke:black;" points="334,-104.5 264,-104.5 264,-83.5 334,-83.5 334,-104.5"/>
<text text-anchor="middle" x="299" y="-91" style="font-family:Arial;font-size:10.00;">jamesXPath</text>
</g>
<!-- analyze&#45;&gt;jamesXPath -->
<g id="edge16" class="edge"><title>analyze&#45;&gt;jamesXPath</title>
<path style="fill:none;stroke:black;" d="M386,-123C372,-119 355,-113 340,-108"/>
<polygon style="fill:black;stroke:black;" points="340.584,-104.521 330,-105 338.573,-111.226 340.584,-104.521"/>
</g>
<!-- jamesXPath_2 -->
<g id="node12" class="node"><title>jamesXPath_2</title>
<polygon style="fill:#eec591;stroke:black;" points="479,-104.5 397,-104.5 397,-83.5 479,-83.5 479,-104.5"/>
<text text-anchor="middle" x="438" y="-91" style="font-family:Arial;font-size:10.00;">jamesXPath_2</text>
</g>
<!-- analyze&#45;&gt;jamesXPath_2 -->
<g id="edge28" class="edge"><title>analyze&#45;&gt;jamesXPath_2</title>
<path style="fill:none;stroke:black;" d="M419,-121C421,-119 423,-116 425,-113"/>
<polygon style="fill:black;stroke:black;" points="427.8,-115.1 431,-105 422.2,-110.9 427.8,-115.1"/>
</g>
<!-- filter_value -->
<g id="node3" class="node"><title>filter_value</title>
<polygon style="fill:lightsteelblue;stroke:black;" points="420,-180.5 352,-180.5 352,-159.5 420,-159.5 420,-180.5"/>
<text text-anchor="middle" x="386" y="-167" style="font-family:Arial;font-size:10.00;">filter_value</text>
</g>
<!-- filter_value&#45;&gt;analyze -->
<g id="edge6" class="edge"><title>filter_value&#45;&gt;analyze</title>
<path style="fill:none;stroke:black;" d="M393,-159C395,-157 397,-154 399,-151"/>
<polygon style="fill:black;stroke:black;" points="401.8,-153.1 405,-143 396.2,-148.9 401.8,-153.1"/>
</g>
<!-- input_format_value -->
<g id="node4" class="node"><title>input_format_value</title>
<polygon style="fill:lightsteelblue;stroke:black;" points="530,-180.5 424,-180.5 424,-159.5 530,-159.5 530,-180.5"/>
<text text-anchor="middle" x="477" y="-167" style="font-family:Arial;font-size:10.00;">input_format_value</text>
</g>
<!-- input_format_value&#45;&gt;analyze -->
<g id="edge8" class="edge"><title>input_format_value&#45;&gt;analyze</title>
<path style="fill:none;stroke:black;" d="M459,-159C453,-156 446,-152 440,-148"/>
<polygon style="fill:black;stroke:black;" points="441.441,-144.797 431,-143 438.042,-150.916 441.441,-144.797"/>
</g>
<!-- output_format_value -->
<g id="node5" class="node"><title>output_format_value</title>
<polygon style="fill:lightsteelblue;stroke:black;" points="644,-180.5 534,-180.5 534,-159.5 644,-159.5 644,-180.5"/>
<text text-anchor="middle" x="589" y="-167" style="font-family:Arial;font-size:10.00;">output_format_value</text>
</g>
<!-- output_format_value&#45;&gt;analyze -->
<g id="edge10" class="edge"><title>output_format_value&#45;&gt;analyze</title>
<path style="fill:none;stroke:black;" d="M534,-160C532,-159 531,-159 530,-159 493,-152 482,-153 448,-144"/>
<polygon style="fill:black;stroke:black;" points="448.492,-140.529 438,-142 447.119,-147.393 448.492,-140.529"/>
</g>
<!-- stoplist_value -->
<g id="node6" class="node"><title>stoplist_value</title>
<polygon style="fill:lightsteelblue;stroke:black;" points="728,-180.5 648,-180.5 648,-159.5 728,-159.5 728,-180.5"/>
<text text-anchor="middle" x="688" y="-167" style="font-family:Arial;font-size:10.00;">stoplist_value</text>
</g>
<!-- stoplist_value&#45;&gt;analyze -->
<g id="edge12" class="edge"><title>stoplist_value&#45;&gt;analyze</title>
<path style="fill:none;stroke:black;" d="M648,-160C646,-159 645,-159 644,-159 558,-145 531,-161 448,-144"/>
<polygon style="fill:black;stroke:black;" points="448.492,-140.529 438,-142 447.119,-147.393 448.492,-140.529"/>
</g>
<!-- WORKFLOWINTERNALSINK_termCandidatesAboveThreshold -->
<g id="node20" class="node"><title>WORKFLOWINTERNALSINK_termCandidatesAboveThreshold</title>
<polygon style="fill:#bcd2ee;stroke:black;" points="382,-45.5 216,-45.5 216,-24.5 382,-24.5 382,-45.5"/>
<text text-anchor="middle" x="299" y="-32" style="font-family:Arial;font-size:10.00;">termCandidatesAboveThreshold</text>
</g>
<!-- jamesXPath&#45;&gt;WORKFLOWINTERNALSINK_termCandidatesAboveThreshold -->
<g id="edge32" class="edge"><title>jamesXPath&#45;&gt;WORKFLOWINTERNALSINK_termCandidatesAboveThreshold</title>
<path style="fill:none;stroke:black;" d="M299,-83C299,-75 299,-65 299,-56"/>
<polygon style="fill:black;stroke:black;" points="302.5,-56 299,-46 295.5,-56 302.5,-56"/>
</g>
<!-- Concatenate_two_strings -->
<g id="node8" class="node"><title>Concatenate_two_strings</title>
<polygon style="fill:white;stroke:black;" points="132,-180.5 5.68434e-14,-180.5 0,-159.5 132,-159.5 132,-180.5"/>
<text text-anchor="middle" x="66" y="-167" style="font-family:Arial;font-size:10.00;">Concatenate_two_strings</text>
</g>
<!-- Concatenate_two_strings_2 -->
<g id="node10" class="node"><title>Concatenate_two_strings_2</title>
<polygon style="fill:white;stroke:black;" points="248,-142.5 104,-142.5 104,-121.5 248,-121.5 248,-142.5"/>
<text text-anchor="middle" x="176" y="-129" style="font-family:Arial;font-size:10.00;">Concatenate_two_strings_2</text>
</g>
<!-- Concatenate_two_strings&#45;&gt;Concatenate_two_strings_2 -->
<g id="edge24" class="edge"><title>Concatenate_two_strings&#45;&gt;Concatenate_two_strings_2</title>
<path style="fill:none;stroke:black;" d="M97,-159C109,-155 123,-150 135,-146"/>
<polygon style="fill:black;stroke:black;" points="136.427,-149.226 145,-143 134.416,-142.521 136.427,-149.226"/>
</g>
<!-- xpath_first_bit -->
<g id="node9" class="node"><title>xpath_first_bit</title>
<polygon style="fill:lightsteelblue;stroke:black;" points="107,-218.5 25,-218.5 25,-197.5 107,-197.5 107,-218.5"/>
<text text-anchor="middle" x="66" y="-205" style="font-family:Arial;font-size:10.00;">xpath_first_bit</text>
</g>
<!-- xpath_first_bit&#45;&gt;Concatenate_two_strings -->
<g id="edge22" class="edge"><title>xpath_first_bit&#45;&gt;Concatenate_two_strings</title>
<path style="fill:none;stroke:black;" d="M66,-197C66,-195 66,-193 66,-191"/>
<polygon style="fill:black;stroke:black;" points="69.5001,-191 66,-181 62.5001,-191 69.5001,-191"/>
</g>
<!-- Concatenate_two_strings_2&#45;&gt;jamesXPath -->
<g id="edge18" class="edge"><title>Concatenate_two_strings_2&#45;&gt;jamesXPath</title>
<path style="fill:none;stroke:black;" d="M210,-121C224,-117 240,-112 255,-108"/>
<polygon style="fill:black;stroke:black;" points="256.427,-111.226 265,-105 254.416,-104.521 256.427,-111.226"/>
</g>
<!-- WORKFLOWINTERNALSINK_xpathOutput -->
<g id="node21" class="node"><title>WORKFLOWINTERNALSINK_xpathOutput</title>
<polygon style="fill:#bcd2ee;stroke:black;" points="212,-45.5 140,-45.5 140,-24.5 212,-24.5 212,-45.5"/>
<text text-anchor="middle" x="176" y="-32" style="font-family:Arial;font-size:10.00;">xpathOutput</text>
</g>
<!-- Concatenate_two_strings_2&#45;&gt;WORKFLOWINTERNALSINK_xpathOutput -->
<g id="edge34" class="edge"><title>Concatenate_two_strings_2&#45;&gt;WORKFLOWINTERNALSINK_xpathOutput</title>
<path style="fill:none;stroke:black;" d="M176,-121C176,-105 176,-76 176,-56"/>
<polygon style="fill:black;stroke:black;" points="179.5,-56 176,-46 172.5,-56 179.5,-56"/>
</g>
<!-- xpath_last_bit -->
<g id="node11" class="node"><title>xpath_last_bit</title>
<polygon style="fill:lightsteelblue;stroke:black;" points="216,-180.5 136,-180.5 136,-159.5 216,-159.5 216,-180.5"/>
<text text-anchor="middle" x="176" y="-167" style="font-family:Arial;font-size:10.00;">xpath_last_bit</text>
</g>
<!-- xpath_last_bit&#45;&gt;Concatenate_two_strings_2 -->
<g id="edge26" class="edge"><title>xpath_last_bit&#45;&gt;Concatenate_two_strings_2</title>
<path style="fill:none;stroke:black;" d="M176,-159C176,-157 176,-155 176,-153"/>
<polygon style="fill:black;stroke:black;" points="179.5,-153 176,-143 172.5,-153 179.5,-153"/>
</g>
<!-- WORKFLOWINTERNALSINK_allTermCandidates -->
<g id="node22" class="node"><title>WORKFLOWINTERNALSINK_allTermCandidates</title>
<polygon style="fill:#bcd2ee;stroke:black;" points="490,-45.5 386,-45.5 386,-24.5 490,-24.5 490,-45.5"/>
<text text-anchor="middle" x="438" y="-32" style="font-family:Arial;font-size:10.00;">allTermCandidates</text>
</g>
<!-- jamesXPath_2&#45;&gt;WORKFLOWINTERNALSINK_allTermCandidates -->
<g id="edge36" class="edge"><title>jamesXPath_2&#45;&gt;WORKFLOWINTERNALSINK_allTermCandidates</title>
<path style="fill:none;stroke:black;" d="M438,-83C438,-75 438,-65 438,-56"/>
<polygon style="fill:black;stroke:black;" points="441.5,-56 438,-46 434.5,-56 441.5,-56"/>
</g>
<!-- xPathString_value -->
<g id="node13" class="node"><title>xPathString_value</title>
<polygon style="fill:lightsteelblue;stroke:black;" points="542,-142.5 442,-142.5 442,-121.5 542,-121.5 542,-142.5"/>
<text text-anchor="middle" x="492" y="-129" style="font-family:Arial;font-size:10.00;">xPathString_value</text>
</g>
<!-- xPathString_value&#45;&gt;jamesXPath_2 -->
<g id="edge30" class="edge"><title>xPathString_value&#45;&gt;jamesXPath_2</title>
<path style="fill:none;stroke:black;" d="M477,-121C472,-118 467,-114 461,-110"/>
<polygon style="fill:black;stroke:black;" points="463.335,-107.332 453,-105 459.625,-113.268 463.335,-107.332"/>
</g>
<!-- WORKFLOWINTERNALSOURCECONTROL -->
<g id="node15" class="node"><title>WORKFLOWINTERNALSOURCECONTROL</title>
<polygon style="fill:#ff4040;stroke:black;" points="322,-215 315,-204.5 329,-204.5 322,-215"/>
</g>
<!-- WORKFLOWINTERNALSOURCE_sentencesList -->
<g id="node16" class="node"><title>WORKFLOWINTERNALSOURCE_sentencesList</title>
<polygon style="fill:skyblue;stroke:black;" points="311,-218.5 231,-218.5 231,-197.5 311,-197.5 311,-218.5"/>
<text text-anchor="middle" x="271" y="-205" style="font-family:Arial;font-size:10.00;">sentencesList</text>
</g>
<!-- WORKFLOWINTERNALSOURCE_sentencesList&#45;&gt;sentenceListNormaliser -->
<g id="edge4" class="edge"><title>WORKFLOWINTERNALSOURCE_sentencesList&#45;&gt;sentenceListNormaliser</title>
<path style="fill:none;stroke:black;" d="M275,-197C276,-195 277,-193 277,-191"/>
<polygon style="fill:black;stroke:black;" points="280.536,-191.585 281,-181 274.036,-188.985 280.536,-191.585"/>
</g>
<!-- WORKFLOWINTERNALSOURCE_cValueThreshold -->
<g id="node17" class="node"><title>WORKFLOWINTERNALSOURCE_cValueThreshold</title>
<polygon style="fill:skyblue;stroke:black;" points="227,-218.5 131,-218.5 131,-197.5 227,-197.5 227,-218.5"/>
<text text-anchor="middle" x="179" y="-205" style="font-family:Arial;font-size:10.00;">cValueThreshold</text>
</g>
<!-- WORKFLOWINTERNALSOURCE_cValueThreshold&#45;&gt;Concatenate_two_strings -->
<g id="edge20" class="edge"><title>WORKFLOWINTERNALSOURCE_cValueThreshold&#45;&gt;Concatenate_two_strings</title>
<path style="fill:none;stroke:black;" d="M152,-197C144,-195 135,-191 127,-189 122,-187 117,-185 113,-184"/>
<polygon style="fill:black;stroke:black;" points="113.584,-180.521 103,-181 111.573,-187.226 113.584,-180.521"/>
</g>
<!-- WORKFLOWINTERNALSINKCONTROL -->
<g id="node19" class="node"><title>WORKFLOWINTERNALSINKCONTROL</title>
<polygon style="fill:#66cd00;stroke:black;" points="501,-28 508,-38.5 494,-38.5 501,-28"/>
</g>
</g>
</svg>
