<?xml version="1.0" encoding="UTF-8" standalone="no"?>
<!DOCTYPE svg PUBLIC "-//W3C//DTD SVG 1.0//EN"
 "http://www.w3.org/TR/2001/REC-SVG-20010904/DTD/svg10.dtd" [
 <!ATTLIST svg xmlns:xlink CDATA #FIXED "http://www.w3.org/1999/xlink">
]>
<!-- Generated by Graphviz version 2.14.1 (Fri Sep  7 12:22:15 UTC 2007)
     For user: (myexperiment) myExperiment User -->
<!-- Title: scufl_graph Pages: 1 -->
<svg width="567pt" height="226pt"
 viewBox="0.00 0.00 567.00 226.00" xmlns="http://www.w3.org/2000/svg" xmlns:xlink="http://www.w3.org/1999/xlink">
<g id="graph0" class="graph" transform="scale(1 1) rotate(0) translate(4 222)">
<title>scufl_graph</title>
<polygon style="fill:white;stroke:white;" points="-4,4 -4,-222 563,-222 563,4 -4,4"/>
<g id="cluster2" class="cluster"><title>cluster_sources</title>
<polygon style="fill:none;stroke:black;stroke-dasharray:1,5;" points="293,-151 293,-210 551,-210 551,-151 293,-151"/>
<text text-anchor="middle" x="337" y="-197" style="font-family:Arial;font-size:10.00;">Workflow Inputs</text>
</g>
<g id="cluster3" class="cluster"><title>cluster_sinks</title>
<polygon style="fill:none;stroke:black;stroke-dasharray:1,5;" points="22,-16 22,-75 420,-75 420,-16 22,-16"/>
<text text-anchor="middle" x="70" y="-62" style="font-family:Arial;font-size:10.00;">Workflow Outputs</text>
</g>
<!-- getSupportedDBs -->
<g id="node1" class="node"><title>getSupportedDBs</title>
<polygon style="fill:#a2cd5a;stroke:black;" points="98,-104.5 4.9738e-14,-104.5 0,-83.5 98,-83.5 98,-104.5"/>
<text text-anchor="middle" x="49" y="-91" style="font-family:Arial;font-size:10.00;">getSupportedDBs</text>
</g>
<!-- WORKFLOWINTERNALSINK_SupportedDBs -->
<g id="node12" class="node"><title>WORKFLOWINTERNALSINK_SupportedDBs</title>
<polygon style="fill:#bcd2ee;stroke:black;" points="112,-45.5 30,-45.5 30,-24.5 112,-24.5 112,-45.5"/>
<text text-anchor="middle" x="71" y="-32" style="font-family:Arial;font-size:10.00;">SupportedDBs</text>
</g>
<!-- getSupportedDBs&#45;&gt;WORKFLOWINTERNALSINK_SupportedDBs -->
<g id="edge12" class="edge"><title>getSupportedDBs&#45;&gt;WORKFLOWINTERNALSINK_SupportedDBs</title>
<path style="fill:none;stroke:black;" d="M53,-83C56,-75 60,-64 63,-55"/>
<polygon style="fill:black;stroke:black;" points="66.1369,-56.5596 67,-46 59.7402,-53.7166 66.1369,-56.5596"/>
</g>
<!-- getSupportedFormats -->
<g id="node2" class="node"><title>getSupportedFormats</title>
<polygon style="fill:#a2cd5a;stroke:black;" points="218,-104.5 102,-104.5 102,-83.5 218,-83.5 218,-104.5"/>
<text text-anchor="middle" x="160" y="-91" style="font-family:Arial;font-size:10.00;">getSupportedFormats</text>
</g>
<!-- WORKFLOWINTERNALSINK_SupportedFormats -->
<g id="node13" class="node"><title>WORKFLOWINTERNALSINK_SupportedFormats</title>
<polygon style="fill:#bcd2ee;stroke:black;" points="218,-45.5 116,-45.5 116,-24.5 218,-24.5 218,-45.5"/>
<text text-anchor="middle" x="167" y="-32" style="font-family:Arial;font-size:10.00;">SupportedFormats</text>
</g>
<!-- getSupportedFormats&#45;&gt;WORKFLOWINTERNALSINK_SupportedFormats -->
<g id="edge14" class="edge"><title>getSupportedFormats&#45;&gt;WORKFLOWINTERNALSINK_SupportedFormats</title>
<path style="fill:none;stroke:black;" d="M161,-83C162,-75 163,-65 164,-56"/>
<polygon style="fill:black;stroke:black;" points="167.471,-56.4922 166,-46 160.607,-55.1194 167.471,-56.4922"/>
</g>
<!-- getSupportedStyles -->
<g id="node3" class="node"><title>getSupportedStyles</title>
<polygon style="fill:#a2cd5a;stroke:black;" points="330,-104.5 222,-104.5 222,-83.5 330,-83.5 330,-104.5"/>
<text text-anchor="middle" x="276" y="-91" style="font-family:Arial;font-size:10.00;">getSupportedStyles</text>
</g>
<!-- WORKFLOWINTERNALSINK_SupportedStyles -->
<g id="node14" class="node"><title>WORKFLOWINTERNALSINK_SupportedStyles</title>
<polygon style="fill:#bcd2ee;stroke:black;" points="316,-45.5 222,-45.5 222,-24.5 316,-24.5 316,-45.5"/>
<text text-anchor="middle" x="269" y="-32" style="font-family:Arial;font-size:10.00;">SupportedStyles</text>
</g>
<!-- getSupportedStyles&#45;&gt;WORKFLOWINTERNALSINK_SupportedStyles -->
<g id="edge16" class="edge"><title>getSupportedStyles&#45;&gt;WORKFLOWINTERNALSINK_SupportedStyles</title>
<path style="fill:none;stroke:black;" d="M275,-83C274,-75 273,-65 272,-56"/>
<polygon style="fill:black;stroke:black;" points="275.393,-55.1194 270,-46 268.529,-56.4922 275.393,-55.1194"/>
</g>
<!-- fetchBatch -->
<g id="node4" class="node"><title>fetchBatch</title>
<polygon style="fill:#a2cd5a;stroke:black;" points="439,-142.5 375,-142.5 375,-121.5 439,-121.5 439,-142.5"/>
<text text-anchor="middle" x="407" y="-129" style="font-family:Arial;font-size:10.00;">fetchBatch</text>
</g>
<!-- Merge_string_list_to_string -->
<g id="node5" class="node"><title>Merge_string_list_to_string</title>
<polygon style="fill:#d15fee;stroke:black;" points="480,-104.5 334,-104.5 334,-83.5 480,-83.5 480,-104.5"/>
<text text-anchor="middle" x="407" y="-91" style="font-family:Arial;font-size:10.00;">Merge_string_list_to_string</text>
</g>
<!-- fetchBatch&#45;&gt;Merge_string_list_to_string -->
<g id="edge8" class="edge"><title>fetchBatch&#45;&gt;Merge_string_list_to_string</title>
<path style="fill:none;stroke:black;" d="M407,-121C407,-119 407,-117 407,-115"/>
<polygon style="fill:black;stroke:black;" points="410.5,-115 407,-105 403.5,-115 410.5,-115"/>
</g>
<!-- WORKFLOWINTERNALSINK_DataFetched -->
<g id="node15" class="node"><title>WORKFLOWINTERNALSINK_DataFetched</title>
<polygon style="fill:#bcd2ee;stroke:black;" points="394,-45.5 320,-45.5 320,-24.5 394,-24.5 394,-45.5"/>
<text text-anchor="middle" x="357" y="-32" style="font-family:Arial;font-size:10.00;">DataFetched</text>
</g>
<!-- Merge_string_list_to_string&#45;&gt;WORKFLOWINTERNALSINK_DataFetched -->
<g id="edge10" class="edge"><title>Merge_string_list_to_string&#45;&gt;WORKFLOWINTERNALSINK_DataFetched</title>
<path style="fill:none;stroke:black;" d="M398,-83C391,-74 381,-63 373,-54"/>
<polygon style="fill:black;stroke:black;" points="375.219,-51.221 366,-46 369.951,-55.8306 375.219,-51.221"/>
</g>
<!-- WORKFLOWINTERNALSOURCECONTROL -->
<g id="node7" class="node"><title>WORKFLOWINTERNALSOURCECONTROL</title>
<polygon style="fill:#ff4040;stroke:black;" points="536,-177 529,-166.5 543,-166.5 536,-177"/>
</g>
<!-- WORKFLOWINTERNALSOURCE_GeneOrProteinSeeked -->
<g id="node8" class="node"><title>WORKFLOWINTERNALSOURCE_GeneOrProteinSeeked</title>
<polygon style="fill:skyblue;stroke:black;" points="525,-180.5 403,-180.5 403,-159.5 525,-159.5 525,-180.5"/>
<text text-anchor="middle" x="464" y="-167" style="font-family:Arial;font-size:10.00;">GeneOrProteinSeeked</text>
</g>
<!-- WORKFLOWINTERNALSOURCE_GeneOrProteinSeeked&#45;&gt;fetchBatch -->
<g id="edge6" class="edge"><title>WORKFLOWINTERNALSOURCE_GeneOrProteinSeeked&#45;&gt;fetchBatch</title>
<path style="fill:none;stroke:black;" d="M448,-159C443,-156 437,-152 432,-148"/>
<polygon style="fill:black;stroke:black;" points="433.441,-144.797 423,-143 430.042,-150.916 433.441,-144.797"/>
</g>
<!-- WORKFLOWINTERNALSOURCE_DatabaseToQuery -->
<g id="node9" class="node"><title>WORKFLOWINTERNALSOURCE_DatabaseToQuery</title>
<polygon style="fill:skyblue;stroke:black;" points="399,-180.5 301,-180.5 301,-159.5 399,-159.5 399,-180.5"/>
<text text-anchor="middle" x="350" y="-167" style="font-family:Arial;font-size:10.00;">DatabaseToQuery</text>
</g>
<!-- WORKFLOWINTERNALSOURCE_DatabaseToQuery&#45;&gt;fetchBatch -->
<g id="edge4" class="edge"><title>WORKFLOWINTERNALSOURCE_DatabaseToQuery&#45;&gt;fetchBatch</title>
<path style="fill:none;stroke:black;" d="M366,-159C371,-156 377,-152 382,-148"/>
<polygon style="fill:black;stroke:black;" points="383.958,-150.916 391,-143 380.559,-144.797 383.958,-150.916"/>
</g>
<!-- WORKFLOWINTERNALSINKCONTROL -->
<g id="node11" class="node"><title>WORKFLOWINTERNALSINKCONTROL</title>
<polygon style="fill:#66cd00;stroke:black;" points="405,-28 412,-38.5 398,-38.5 405,-28"/>
</g>
</g>
</svg>
